CHANGES.txt
LICENCE.txt
README.md
setup.py
pu_in_core/README
pu_in_core/__init__.py
pu_in_core.egg-info/PKG-INFO
pu_in_core.egg-info/SOURCES.txt
pu_in_core.egg-info/dependency_links.txt
pu_in_core.egg-info/not-zip-safe
pu_in_core.egg-info/requires.txt
pu_in_core.egg-info/top_level.txt
pu_in_core/static/js/pu_in_core.js
pu_in_core/views/__init__.py
pu_in_core/views/inlineaction.py
pu_in_core/views/jsonbase.py