Metadata-Version: 1.1
Name: pu-in-core
Version: 1.0.2
Summary: PythonUnited Intranet Core
Home-page: https://github.com/PythonUnited/pu.intranet.core
Author: PythonUnited
Author-email: info@pythonunited.com
License: beer-ware
Keywords: Django Intranet Core
Platform: UNKNOWN
Classifier: Development Status :: 5 - Production/Stable
Classifier: Framework :: Django
Classifier: Intended Audience :: Developers
Classifier: License :: Freely Distributable
Classifier: Programming Language :: Python
Classifier: Topic :: Internet :: WWW/HTTP :: Site Management
Classifier: Topic :: Software Development :: Libraries :: Application Frameworks
